{
    "status": 200,
    "message": "Success",
    "data": [
        {
            "key": "outstanding",
            "name": "卓越（2分）",
            "is_require": 0
        },
        {
            "key": "excellence",
            "name": "优秀（1.5分）",
            "is_require": 0
        },
        {
            "key": "good",
            "name": "良好（1分）",
            "is_require": 0
        },
        {
            "key": "to_be_improved",
            "name": "待改进（0.5分）",
            "is_require": 0
        },
        {
            "key": "disqualification",
            "name": "不合格（0分）",
            "is_require": 0
        }
    ]
}